pytest_review/__init__.py
pytest_review/config.py
pytest_review/plugin.py
pytest_review/scoring.py
pytest_review/analyzers/__init__.py
pytest_review/analyzers/assertions.py
pytest_review/analyzers/base.py
pytest_review/analyzers/complexity.py
pytest_review/analyzers/isolation.py
pytest_review/analyzers/naming.py
pytest_review/analyzers/patterns.py
pytest_review/analyzers/performance.py
pytest_review/analyzers/smells.py
pytest_review/collectors/__init__.py
pytest_review/collectors/dynamic.py
pytest_review/reporters/__init__.py
pytest_review/reporters/html.py
pytest_review/reporters/json.py
pytest_review/reporters/terminal.py
pytest_review-0.1.1.dist-info/METADATA
pytest_review-0.1.1.dist-info/WHEEL
pytest_review-0.1.1.dist-info/entry_points.txt
pytest_review-0.1.1.dist-info/licenses/LICENSE
pytest_review-0.1.1.dist-info/RECORD
