Metadata-Version: 2.4
Name: pytest-review
Version: 0.1.1
Summary: A pytest plugin that reviews the quality of your tests
Project-URL: Homepage, https://github.com/shakfu/pytest-review
Project-URL: Repository, https://github.com/shakfu/pytest-review
Author-email: Shakeeb Alireza <me@example.org>
License-Expression: MIT
License-File: LICENSE
Keywords: code-quality,code-review,linter,pytest,pytest-plugin,static-analysis,test-quality,testing
Classifier: Development Status :: 3 - Alpha
Classifier: Framework :: Pytest
Classifier: Intended Audience :: Developers
Classifier: License :: OSI Approved :: MIT License
Classifier: Operating System :: OS Independent
Classifier: Programming Language :: Python :: 3
Classifier: Programming Language :: Python :: 3.9
Classifier: Programming Language :: Python :: 3.10
Classifier: Programming Language :: Python :: 3.11
Classifier: Programming Language :: Python :: 3.12
Classifier: Programming Language :: Python :: 3.13
Classifier: Topic :: Software Development :: Testing
Requires-Python: >=3.9
Requires-Dist: pytest>=7.0.0
